{"resource": "boxscore", "parameters": {"GameID": "0021800390", "StartPeriod": 0, "EndPeriod": 14, "StartRange": 0, "EndRange": 2147483647, "RangeType": 0}, "resultSets": [{"name": "PlayerStats", "headers": ["GAME_ID", "TEAM_ID", "TEAM_ABBREVIATION", "TEAM_CITY", "PLAYER_ID", "PLAYER_NAME", "START_POSITION", "COMMENT", "MIN", "FGM", "FGA", "FG_PCT", "FG3M", "FG3A", "FG3_PCT", "FTM", "FTA", "FT_PCT", "OREB", "DREB", "REB", "AST", "STL", "BLK", "TO", "PF", "PTS", "PLUS_MINUS"], "rowSet": [["0021800390", 1610612762, "UTA", "Utah", 204060, "Joe Ingles", "F", "", null, null, null, null, null, null, null, null, null, null, null, null, null, null, null, null, null, null, null, null], ["0021800390", 1610612762, "UTA", "Utah", 202324, "Derrick Favors", "F", "", null, null, null, null, null, null, null, null, null, null, null, null, null, null, null, null, null, null, null, null], ["0021800390", 1610612762, "UTA", "Utah", 203497, "Rudy Gobert", "C", "", null, null, null, null, null, null, null, null, null, null, null, null, null, null, null, null, null, null, null, null], ["0021800390", 1610612762, "UTA", "Utah", 1628378, "Donovan Mitchell", "G", "", null, null, null, null, null, null, null, null, null, null, null, null, null, null, null, null, null, null, null, null], ["0021800390", 1610612762, "UTA", "Utah", 201937, "Ricky Rubio", "G", "", null, null, null, null, null, null, null, null, null, null, null, null, null, null, null, null, null, null, null, null], ["0021800390", 1610612762, "UTA", "Utah", 203109, "Jae Crowder", "", "", null, null, null, null, null, null, null, null, null, null, null, null, null, null, null, null, null, null, null, null], ["0021800390", 1610612762, "UTA", "Utah", 1626220, "Royce O'Neale", "", "", null, null, null, null, null, null, null, null, null, null, null, null, null, null, null, null, null, null, null, null], ["0021800390", 1610612762, "UTA", "Utah", 2594, "Kyle Korver", "", "", null, null, null, null, null, null, null, null, null, null, null, null, null, null, null, null, null, null, null, null], ["0021800390", 1610612762, "UTA", "Utah", 203957, "Dante Exum", "", "", null, null, null, null, null, null, null, null, null, null, null, null, null, null, null, null, null, null, null, null], ["0021800390", 1610612762, "UTA", "Utah", 200757, "Thabo Sefolosha", "", "", null, null, null, null, null, null, null, null, null, null, null, null, null, null, null, null, null, null, null, null], ["0021800390", 1610612762, "UTA", "Utah", 1628960, "Grayson Allen", "", "DNP - Coach's Decision                  ", null, null, null, null, null, null, null, null, null, null, null, null, null, null, null, null, null, null, null, null], ["0021800390", 1610612762, "UTA", "Utah", 203526, "Raul Neto", "", "DNP - Coach's Decision                  ", null, null, null, null, null, null, null, null, null, null, null, null, null, null, null, null, null, null, null, null], ["0021800390", 1610612762, "UTA", "Utah", 202327, "Ekpe Udoh", "", "DNP - Coach's Decision                  ", null, null, null, null, null, null, null, null, null, null, null, null, null, null, null, null, null, null, null, null], ["0021800390", 1610612759, "SAS", "San Antonio", 1628401, "Derrick White", "F", "", null, null, null, null, null, null, null, null, null, null, null, null, null, null, null, null, null, null, null, null], ["0021800390", 1610612759, "SAS", "San Antonio", 200752, "Rudy Gay", "F", "", null, null, null, null, null, null, null, null, null, null, null, null, null, null, null, null, null, null, null, null], ["0021800390", 1610612759, "SAS", "San Antonio", 200746, "LaMarcus Aldridge", "C", "", null, null, null, null, null, null, null, null, null, null, null, null, null, null, null, null, null, null, null, null], ["0021800390", 1610612759, "SAS", "San Antonio", 201942, "DeMar DeRozan", "G", "", null, null, null, null, null, null, null, null, null, null, null, null, null, null, null, null, null, null, null, null], ["0021800390", 1610612759, "SAS", "San Antonio", 1627854, "Bryn Forbes", "G", "", null, null, null, null, null, null, null, null, null, null, null, null, null, null, null, null, null, null, null, null], ["0021800390", 1610612759, "SAS", "San Antonio", 201988, "Patty Mills", "", "", null, null, null, null, null, null, null, null, null, null, null, null, null, null, null, null, null, null, null, null], ["0021800390", 1610612759, "SAS", "San Antonio", 201158, "Marco Belinelli", "", "", null, null, null, null, null, null, null, null, null, null, null, null, null, null, null, null, null, null, null, null], ["0021800390", 1610612759, "SAS", "San Antonio", 1629002, "Chimezie Metu", "", "", null, null, null, null, null, null, null, null, null, null, null, null, null, null, null, null, null, null, null, null], ["0021800390", 1610612759, "SAS", "San Antonio", 1627751, "Jakob Poeltl", "", "", null, null, null, null, null, null, null, null, null, null, null, null, null, null, null, null, null, null, null, null], ["0021800390", 1610612759, "SAS", "San Antonio", 202722, "Davis Bertans", "", "NWT - Personal                          ", null, null, null, null, null, null, null, null, null, null, null, null, null, null, null, null, null, null, null, null], ["0021800390", 1610612759, "SAS", "San Antonio", 201967, "Dante Cunningham", "", "DND - Injury/Illness                    ", null, null, null, null, null, null, null, null, null, null, null, null, null, null, null, null, null, null, null, null], ["0021800390", 1610612759, "SAS", "San Antonio", 1629234, "Drew Eubanks", "", "DNP - Coach's Decision                  ", null, null, null, null, null, null, null, null, null, null, null, null, null, null, null, null, null, null, null, null], ["0021800390", 1610612759, "SAS", "San Antonio", 202347, "Quincy Pondexter", "", "DNP - Coach's Decision                  ", null, null, null, null, null, null, null, null, null, null, null, null, null, null, null, null, null, null, null, null]]}, {"name": "TeamStats", "headers": ["GAME_ID", "TEAM_ID", "TEAM_NAME", "TEAM_ABBREVIATION", "TEAM_CITY", "MIN", "FGM", "FGA", "FG_PCT", "FG3M", "FG3A", "FG3_PCT", "FTM", "FTA", "FT_PCT", "OREB", "DREB", "REB", "AST", "STL", "BLK", "TO", "PF", "PTS", "PLUS_MINUS"], "rowSet": [["0021800390", 1610612762, "Jazz", "UTA", "Utah", null, null, null, null, null, null, null, null, null, null, null, null, null, null, null, null, null, null, null, null], ["0021800390", 1610612759, "Spurs", "SAS", "San Antonio", null, null, null, null, null, null, null, null, null, null, null, null, null, null, null, null, null, null, null, null]]}, {"name": "TeamStarterBenchStats", "headers": ["GAME_ID", "TEAM_ID", "TEAM_NAME", "TEAM_ABBREVIATION", "TEAM_CITY", "STARTERS_BENCH", "MIN", "FGM", "FGA", "FG_PCT", "FG3M", "FG3A", "FG3_PCT", "FTM", "FTA", "FT_PCT", "OREB", "DREB", "REB", "AST", "STL", "BLK", "TO", "PF", "PTS"], "rowSet": [["0021800390", 1610612762, "Jazz", "UTA", "Utah", "Starters", null, null, null, null, null, null, null, null, null, null, null, null, null, null, null, null, null, null, null], ["0021800390", 1610612762, "Jazz", "UTA", "Utah", "Bench", null, null, null, null, null, null, null, null, null, null, null, null, null, null, null, null, null, null, null], ["0021800390", 1610612759, "Spurs", "SAS", "San Antonio", "Starters", null, null, null, null, null, null, null, null, null, null, null, null, null, null, null, null, null, null, null], ["0021800390", 1610612759, "Spurs", "SAS", "San Antonio", "Bench", null, null, null, null, null, null, null, null, null, null, null, null, null, null, null, null, null, null, null]]}]}